freeplot/__init__.py
freeplot/base.py
freeplot/config.py
freeplot/unit.py
freeplot/utils.py
freeplot/zoo.py
freeplot-0.5.1.dist-info/LICENSE
freeplot-0.5.1.dist-info/METADATA
freeplot-0.5.1.dist-info/WHEEL
freeplot-0.5.1.dist-info/top_level.txt
freeplot-0.5.1.dist-info/RECORD
