Metadata-Version: 2.2
Name: freeplot
Version: 0.5.1
Summary: a Python data visualization library based on matplotlib
Home-page: https://github.com/MTandHJ/freeplot
Author: MTandHJ
Author-email: congxueric@gmail.com
License: MIT License
Classifier: Programming Language :: Python :: 3
Classifier: License :: OSI Approved :: MIT License
Classifier: Operating System :: OS Independent
Requires-Python: >=3.6
License-File: LICENSE
Requires-Dist: SciencePlots==1.0.9
Dynamic: author
Dynamic: author-email
Dynamic: classifier
Dynamic: description
Dynamic: description-content-type
Dynamic: home-page
Dynamic: license
Dynamic: requires-dist
Dynamic: requires-python
Dynamic: summary
